Metadata-Version: 2.1
Name: housing-prediction
Version: 0.4
Summary: A package to train machine learning models on housing dataset
Home-page: https://github.com/rishitoshsingh-ta/mle-training
Author: Rishitosh Kumar Singh
Author-email: Rishitosh Kumar Singh <rishitosh.sing@tigeranalytics.com>
Project-URL: Homepage, https://github.com/rishitoshsingh-ta/mle-training
Project-URL: Bug Tracker, https://github.com/rishitoshsingh-ta/mle-training/issues
Classifier: Programming Language :: Python :: 3
Classifier: License :: OSI Approved :: MIT License
Classifier: Operating System :: OS Independent
Requires-Python: >=3.9
License-File: LICENSE.txt
Requires-Dist: pandas (>=1.4.2)
Requires-Dist: scikit-learn (>=1.0.2)
Requires-Dist: numpy (>=1.22.3)
Requires-Dist: mlflow
